LICENSE.txt
MANIFEST.in
README.md
README.rst
next_prev.py
setup.py
django_next_prev.egg-info/PKG-INFO
django_next_prev.egg-info/SOURCES.txt
django_next_prev.egg-info/dependency_links.txt
django_next_prev.egg-info/not-zip-safe
django_next_prev.egg-info/requires.txt
django_next_prev.egg-info/top_level.txt